poetry_demo/__init__.py
poetry_demo5678-0.1.0.dist-info/METADATA
poetry_demo5678-0.1.0.dist-info/WHEEL
poetry_demo5678-0.1.0.dist-info/RECORD
