Metadata-Version: 2.1
Name: poetry-demo5678
Version: 0.1.0
Summary: 
Author: firstnapat
Author-email: “napatdmsu@gmail.com
Requires-Python: >=3.11,<4.0
Classifier: Programming Language :: Python :: 3
Classifier: Programming Language :: Python :: 3.11
Requires-Dist: pandas (==2.0.1)
Requires-Dist: pyspark (==3.4.0)
